blacksquare/__init__.py
blacksquare/cell.py
blacksquare/crossword.py
blacksquare/html.py
blacksquare/spreadthewordlist.npz
blacksquare/symmetry.py
blacksquare/types.py
blacksquare/utils.py
blacksquare/word.py
blacksquare/word_list.py
blacksquare-0.9.0.dist-info/LICENSE.md
blacksquare-0.9.0.dist-info/METADATA
blacksquare-0.9.0.dist-info/WHEEL
blacksquare-0.9.0.dist-info/top_level.txt
blacksquare-0.9.0.dist-info/RECORD
