Metadata-Version: 2.2
Name: blacksquare
Version: 0.9.0
Summary: A package for creating crossword puzzles
Author-email: Patrick Maher <pmaher86@gmail.com>
Project-URL: Source, https://github.com/pmaher86/blacksquare
Classifier: Programming Language :: Python :: 3
Classifier: License :: OSI Approved :: MIT License
Classifier: Operating System :: OS Independent
Requires-Python: >=3.10
License-File: LICENSE.md
Requires-Dist: networkx
Requires-Dist: numpy
Requires-Dist: pandas
Requires-Dist: puzpy
Requires-Dist: rich
Provides-Extra: dev
Requires-Dist: pre-commit; extra == "dev"
Requires-Dist: pytest; extra == "dev"
Requires-Dist: uv; extra == "dev"
Provides-Extra: pdf
Requires-Dist: pypdf; extra == "pdf"
Requires-Dist: weasyprint; extra == "pdf"
